sr_decorator.py
sr_decorator-0.0.2.dist-info/LICENSE
sr_decorator-0.0.2.dist-info/METADATA
sr_decorator-0.0.2.dist-info/WHEEL
sr_decorator-0.0.2.dist-info/top_level.txt
sr_decorator-0.0.2.dist-info/RECORD
